{
  "name": "Pvp Mystery Box",
  "category": "OTHER",
  "aliases": [ "pmbox" ],
  "required": [
    {
      "id": 6199
    },
    {
      "id": 11694
    },
    {
      "id": 43239
    },
    {
      "id": 29153
    },
    {
      "id": 14484
    },
    {
      "id": 13887
    },
    {
      "id": 13893
    },
    {
      "id": 13899
    },
    {
      "id": 13858
    },
    {
      "id": 13861
    },
    {
      "id": 13864
    },
    {
      "id": 13867
    },
    {
      "id": 13884
    },
    {
      "id": 13890
    },
    {
      "id": 13896
    },
    {
      "id": 13902
    },
    {
      "id": 51902
    },
    {
      "id": 42902
    },
    {
      "id": 29951
    },
    {
      "id": 43237
    },
    {
      "id": 41926
    },
    {
      "id": 41924
    }
  ],
  "type": "OTHER",
  "arg": "pmbox"
}