{
  "guaranteed": [],
  "drops": [
    {
      "id": 557,
      "min": 5,
      "max": 42,
      "rate": 89.0
    },
    {
      "id": 562,
      "min": 2,
      "max": 5,
      "rate": 57.0
    },
    {
      "id": 1452,
      "min": 1,
      "max": 1,
      "rate": 51.0
    },
    {
      "id": 438,
      "min": 1,
      "max": 1,
      "rate": 81.0
    },
    {
      "id": 436,
      "min": 1,
      "max": 1,
      "rate": 75.0
    },
    {
      "id": 2349,
      "min": 1,
      "max": 1,
      "rate": 98.0
    },
    {
      "id": 440,
      "min": 1,
      "max": 1,
      "rate": 83.0
    },
    {
      "id": 2351,
      "min": 1,
      "max": 1,
      "rate": 75.0
    },
    {
      "id": 453,
      "min": 1,
      "max": 1,
      "rate": 83.0
    },
    {
      "id": 447,
      "min": 1,
      "max": 1,
      "rate": 64.0
    },
    {
      "id": 4095,
      "min": 1,
      "max": 1,
      "rate": 4.0
    },
    {
      "id": 830,
      "min": 5,
      "max": 5,
      "rate": 27.0
    },
    {
      "id": 5318,
      "min": 4,
      "max": 4,
      "rate": 98.0
    },
    {
      "id": 5319,
      "min": 4,
      "max": 4,
      "rate": 89.0
    },
    {
      "id": 5324,
      "min": 4,
      "max": 4,
      "rate": 77.0
    },
    {
      "id": 5322,
      "min": 3,
      "max": 3,
      "rate": 67.0
    },
    {
      "id": 5320,
      "min": 3,
      "max": 3,
      "rate": 64.0
    },
    {
      "id": 5323,
      "min": 2,
      "max": 2,
      "rate": 41.0
    },
    {
      "id": 5321,
      "min": 2,
      "max": 2,
      "rate": 35.0
    },
    {
      "id": 995,
      "min": 279,
      "max": 449,
      "rate": 57.0
    },
    {
      "id": 2347,
      "min": 1,
      "max": 1,
      "rate": 93.0
    },
    {
      "id": 1913,
      "min": 1,
      "max": 1,
      "rate": 76.0
    },
    {
      "id": 1623,
      "min": 1,
      "max": 1,
      "rate": 59.0
    },
    {
      "id": 1621,
      "min": 1,
      "max": 1,
      "rate": 58.0
    },
    {
      "id": 1619,
      "min": 1,
      "max": 1,
      "rate": 57.0
    },
    {
      "id": 985,
      "min": 1,
      "max": 1,
      "rate": 59.0
    },
    {
      "id": 987,
      "min": 1,
      "max": 1,
      "rate": 61.0
    },
    {
      "id": 2366,
      "min": 1,
      "max": 1,
      "rate": 3.0
    },
    {
      "id": 1617,
      "min": 1,
      "max": 1,
      "rate": 35.0
    }
  ]
}