{
  "guaranteed": [],
  "drops": [
    {
      "id": 556,
      "min": 11,
      "max": 13,
      "rate": 79.0
    },
    {
      "id": 555,
      "min": 5,
      "max": 9,
      "rate": 83.0
    },
    {
      "id": 561,
      "min": 4,
      "max": 9,
      "rate": 87.0
    },
    {
      "id": 562,
      "min": 1,
      "max": 9,
      "rate": 63.0
    },
    {
      "id": 560,
      "min": 2,
      "max": 2,
      "rate": 63.0
    },
    {
      "id": 9075,
      "min": 3,
      "max": 3,
      "rate": 62.0
    },
    {
      "id": 563,
      "min": 2,
      "max": 2,
      "rate": 64.0
    },
    {
      "id": 4695,
      "min": 3,
      "max": 3,
      "rate": 70.0
    },
    {
      "id": 4696,
      "min": 1,
      "max": 1,
      "rate": 68.0
    },
    {
      "id": 4698,
      "min": 2,
      "max": 2,
      "rate": 73.0
    },
    {
      "id": 559,
      "min": 5,
      "max": 12,
      "rate": 74.0
    },
    {
      "id": 558,
      "min": 5,
      "max": 5,
      "rate": 59.0
    },
    {
      "id": 554,
      "min": 7,
      "max": 7,
      "rate": 68.0
    },
    {
      "id": 565,
      "min": 2,
      "max": 2,
      "rate": 56.0
    },
    {
      "id": 11732,
      "min": 1,
      "max": 1,
      "rate": 32.0
    },
    {
      "id": 2366,
      "min": 1,
      "max": 1,
      "rate": 2.0
    },
    {
      "id": 1249,
      "min": 1,
      "max": 1,
      "rate": 62.0
    },
    {
      "id": 830,
      "min": 5,
      "max": 5,
      "rate": 1.0
    },
    {
      "id": 1247,
      "min": 1,
      "max": 1,
      "rate": 5.0
    },
    {
      "id": 1623,
      "min": 1,
      "max": 1,
      "rate": 69.0
    },
    {
      "id": 1617,
      "min": 1,
      "max": 1,
      "rate": 49.0
    },
    {
      "id": 1619,
      "min": 1,
      "max": 1,
      "rate": 48.0
    },
    {
      "id": 1621,
      "min": 1,
      "max": 1,
      "rate": 25.0
    },
    {
      "id": 7937,
      "min": 23,
      "max": 23,
      "rate": 59.0
    },
    {
      "id": 175,
      "min": 5,
      "max": 5,
      "rate": 57.0
    },
    {
      "id": 1462,
      "min": 1,
      "max": 1,
      "rate": 34.0
    },
    {
      "id": 985,
      "min": 1,
      "max": 1,
      "rate": 28.0
    },
    {
      "id": 987,
      "min": 1,
      "max": 1,
      "rate": 36.0
    }
  ]
}